code_executor_py/__init__.py
code_executor_py/remote_executor.py
code_executor_py/venv_executor.py
code_executor_py-0.3.0.dist-info/METADATA
code_executor_py-0.3.0.dist-info/WHEEL
code_executor_py-0.3.0.dist-info/licenses/LICENSE
code_executor_py-0.3.0.dist-info/RECORD
