Metadata-Version: 2.4
Name: code-executor-py
Version: 0.3.0
Summary: A module for python code execution locally, in separate venv or even separate sandbox container.
Project-URL: homepage, https://github.com/sawradip/code_executor_py
Project-URL: bug_tracker, https://github.com/sawradip/code_executor_py/issues
Author-email: Sawradip Saha <sawradip0@gmail.com>
License-File: LICENSE
Classifier: License :: OSI Approved :: MIT License
Classifier: Operating System :: OS Independent
Classifier: Programming Language :: Python :: 3
Requires-Python: >=3.7
Requires-Dist: fastapi>=0.115.12
Requires-Dist: langchain-core>=0.3
Requires-Dist: pandas>=2.0.0
Requires-Dist: pydantic>=2.0.0
Requires-Dist: uvicorn>=0.34.2
